{"web_url": "http://bits.blogs.nytimes.com/2013/12/06/daily-report-bitcoin-fraud-stays-ahead-of-bitcoin-law/", "snippet": "Illicit activity is rising in the virtual currency market, where there is an increasing amount of real money but few rules and even less oversight.", "lead_paragraph": null, "abstract": "Illicit activity is rising in the virtual currency market, where there is an increasing amount of real money but few rules and even less oversight.", "print_page": null, "blog": [], "source": "The New York Times", "multimedia": [{"width": 600, "url": "images/2011/11/30/technology/bits-daily-report/bits-daily-report-articleLarge.jpg", "height": 400, "subtype": "xlarge", "legacy": {"xlargewidth": "600", "xlarge": "images/2011/11/30/technology/bits-daily-report/bits-daily-report-articleLarge.jpg", "xlargeheight": "400"}, "type": "image"}, {"width": 75, "url": "images/2011/11/30/technology/bits-daily-report/bits-daily-report-thumbStandard.jpg", "height": 75, "subtype": "thumbnail", "legacy": {"thumbnailheight": "75", "thumbnail": "images/2011/11/30/technology/bits-daily-report/bits-daily-report-thumbStandard.jpg", "thumbnailwidth": "75"}, "type": "image"}], "headline": {"main": "Daily Report: Bitcoin Fraud Stays Ahead of Bitcoin Law", "kicker": "Bits"}, "keywords": [], "pub_date": "2013-12-06T06:57:26Z", "document_type": "blogpost", "news_desk": null, "section_name": "Technology", "subsection_name": null, "byline": {"person": [], "original": "By THE NEW YORK TIMES", "organization": "The New York Times"}, "type_of_material": "Blog", "_id": "52a1bc3038f0d84e53acbab1", "word_count": "133", "slideshow_credits": null}