{"web_url": "http://www.nytimes.com/2013/12/08/fashion/weddings/erin-hespe-and-troy-cudworth.html", "snippet": "The bride and groom met at Oxford.", "lead_paragraph": "The bride and groom met at Oxford.", "abstract": null, "print_page": "21", "blog": [], "source": "The New York Times", "multimedia": [{"width": 190, "url": "images/2013/12/08/fashion/weddings/08HESPEjpg/08HESPEjpg-thumbWide.jpg", "height": 126, "subtype": "wide", "legacy": {"wide": "images/2013/12/08/fashion/weddings/08HESPEjpg/08HESPEjpg-thumbWide.jpg", "wideheight": "126", "widewidth": "190"}, "type": "image"}, {"width": 600, "url": "images/2013/12/08/fashion/weddings/08HESPEjpg/08HESPEjpg-articleLarge.jpg", "height": 396, "subtype": "xlarge", "legacy": {"xlargewidth": "600", "xlarge": "images/2013/12/08/fashion/weddings/08HESPEjpg/08HESPEjpg-articleLarge.jpg", "xlargeheight": "396"}, "type": "image"}, {"width": 75, "url": "images/2013/12/08/fashion/weddings/08HESPEjpg/08HESPEjpg-thumbStandard.jpg", "height": 75, "subtype": "thumbnail", "legacy": {"thumbnailheight": "75", "thumbnail": "images/2013/12/08/fashion/weddings/08HESPEjpg/08HESPEjpg-thumbStandard.jpg", "thumbnailwidth": "75"}, "type": "image"}], "headline": {"main": "Erin Hespe and Troy Cudworth", "print_headline": "Erin Hespe, Troy Cudworth"}, "keywords": [{"rank": "1", "is_major": "N", "value": "Weddings and Engagements", "name": "subject"}], "pub_date": "2013-12-08T00:00:00Z", "document_type": "article", "news_desk": "Society", "section_name": "Fashion & Style", "subsection_name": "Weddings/Celebrations", "byline": [], "type_of_material": "News", "_id": "52a4005e38f0d82de675f1f9", "word_count": "207", "slideshow_credits": null}