{"web_url": "http://www.nytimes.com/2013/12/14/opinion/egyptians-are-building-their-future.html", "snippet": "The people of Egypt wish to build a true democracy, and the present draft constitution is a step in the right direction.", "lead_paragraph": "The people of Egypt wish to build a true democracy, and the present draft constitution is a step in the right direction.", "abstract": null, "print_page": "", "blog": [], "source": "The New York Times", "multimedia": [], "headline": {"main": "Egyptians Are Building Their Future", "kicker": "Letters", "print_headline": "Egyptians Are Building Their Future", "content_kicker": "Letters "}, "keywords": [{"rank": "1", "is_major": "N", "value": "Egypt", "name": "glocations"}, {"rank": "3", "is_major": "N", "value": "Japan", "name": "glocations"}, {"rank": "2", "is_major": "N", "value": "Democracy (Theory and Philosophy)", "name": "subject"}], "pub_date": "2013-12-14T00:00:00Z", "document_type": "article", "news_desk": "Letters", "section_name": "Opinion", "subsection_name": null, "byline": [], "type_of_material": "Letter", "_id": "52aae7ec38f0d822c1840087", "word_count": "486", "slideshow_credits": null}